{
  "nodes": [
    {
      "id": "n1",
      "shape": "rect",
      "color": "blue",
      "x": 490.95217446641664,
      "y": 141.03725658778006,
      "w": 160,
      "h": 80.93662999999995,
      "title": "Docente/grupo identifica una oportunidad",
      "sub": "Docente / Investigador",
      "info": "Docente/grupo identifica una oportunidad (convocatoria, invitación de un actor externo, necesidad detectada) o un actor externo (empresa, entidad pública, comunidad) contacta a la Facultad/Instituto.",
      "consideraciones": "",
      "normativa": [],
      "durVal": 0,
      "durUnit": "min",
      "fontFamily": "",
      "fontSize": 0
    },
    {
      "id": "n2",
      "shape": "rect",
      "color": "blue",
      "x": 490.95217446641664,
      "y": 283.73376658778017,
      "w": 160,
      "h": 105.25399999999999,
      "title": "Verificación de pertinencia académica con la Unidad Académica Básica",
      "sub": "",
      "info": "",
      "consideraciones": "",
      "normativa": [],
      "durVal": 5,
      "durUnit": "d",
      "fontFamily": "",
      "fontSize": 0
    },
    {
      "id": "n3",
      "shape": "diamond",
      "color": "blue",
      "x": 485.95217446641664,
      "y": 456.4047665877802,
      "w": 170,
      "h": 90,
      "title": "¿El tema es pertinente?",
      "sub": "",
      "info": "",
      "consideraciones": "",
      "normativa": [],
      "durVal": 0,
      "durUnit": "min",
      "fontFamily": "",
      "fontSize": 0
    },
    {
      "id": "n4",
      "shape": "rect",
      "color": "blue",
      "x": 490.95217446641664,
      "y": 604.9684948637033,
      "w": 160,
      "h": 68.05254999999998,
      "title": "Solicitar autorización DNEIPI",
      "sub": "",
      "info": "",
      "consideraciones": "",
      "normativa": [],
      "durVal": 1,
      "durUnit": "d",
      "fontFamily": "",
      "fontSize": 0
    },
    {
      "id": "n5",
      "shape": "rect",
      "color": "blue",
      "x": 490.95217446641664,
      "y": 715.9210448637032,
      "w": 160,
      "h": 60,
      "title": "Formular propuesta",
      "sub": "Docente director",
      "info": "Formular la propuesta del proyecto en el sistema de información HERMES y enviar al director de la UAB a través del sistema HERMES para su aval.  Se debe tener en cuenta el registro verás y completo de la información solicitada por el sistema, incluyendo la información relacionada al impacto esperado del proyecto, descrito de manera cualitativa y cuantitativa.  \n\nPara la presentación de la propuesta a la Entidad externa se recomienda tener en cuenta la “Guía para la elaboración de propuestas de proyectos y actividades de Extensión” U.GU.06.005.001 en el sistema de información SoftExpert.",
      "consideraciones": "",
      "normativa": [],
      "durVal": 0,
      "durUnit": "min",
      "fontFamily": "",
      "fontSize": 0
    },
    {
      "id": "n6",
      "shape": "rect",
      "color": "blue",
      "x": 490.95217446641664,
      "y": 825.7378175909757,
      "w": 160,
      "h": 77.27272727272721,
      "title": "Solicitar aval de la propuesta",
      "sub": "Docente director",
      "info": "",
      "consideraciones": "",
      "normativa": [],
      "durVal": 20,
      "durUnit": "min",
      "fontFamily": "",
      "fontSize": 0
    },
    {
      "id": "n7",
      "shape": "rect",
      "color": "blue",
      "x": 490.95217446641664,
      "y": 947.5661681134809,
      "w": 160,
      "h": 60,
      "title": "Aval UAB",
      "sub": "Director académico",
      "info": "",
      "consideraciones": "",
      "normativa": [],
      "durVal": 2,
      "durUnit": "d",
      "fontFamily": "",
      "fontSize": 0
    },
    {
      "id": "n8",
      "shape": "rect",
      "color": "blue",
      "x": 490.95217446641664,
      "y": 1046.9705271053529,
      "w": 160,
      "h": 60,
      "title": "Subir aval UAB",
      "sub": "",
      "info": "Subir el aval del director UAB al HERMES ",
      "consideraciones": "",
      "normativa": [],
      "durVal": 20,
      "durUnit": "min",
      "fontFamily": "",
      "fontSize": 0
    },
    {
      "id": "n9",
      "shape": "rect",
      "color": "blue",
      "x": 490.95217446641664,
      "y": 1157.020597927701,
      "w": 160,
      "h": 68.46999999999997,
      "title": "Recomendación Comité",
      "sub": "Docente director",
      "info": "El docente investigador debe hacer la solicitud de presentación de su proyecto al comité mediante el diligenciamiento de un formulario. ",
      "consideraciones": "",
      "normativa": [],
      "durVal": 30,
      "durUnit": "min",
      "fontFamily": "",
      "fontSize": 0
    },
    {
      "id": "n10",
      "shape": "rect",
      "color": "blue",
      "x": 490.95217446641664,
      "y": 1418.9737357659628,
      "w": 160,
      "h": 60,
      "title": "Solicitud de aprobación ante Consejo de sede",
      "sub": "",
      "info": "",
      "consideraciones": "",
      "normativa": [],
      "durVal": 0,
      "durUnit": "min",
      "fontFamily": "",
      "fontSize": 0
    },
    {
      "id": "n12",
      "shape": "diamond",
      "color": "blue",
      "x": 485.95217446641664,
      "y": 1260.984513370144,
      "w": 170,
      "h": 90,
      "title": "¿El comité recomienda solicitud?",
      "sub": "",
      "info": "Recibido el Aval de UAB y la Recomendación del Comité de Investigación y Extensión, si requiere, puede comenzar la Negociación con la Entidad Externa. ",
      "consideraciones": "",
      "normativa": [],
      "durVal": 0,
      "durUnit": "min",
      "fontFamily": "",
      "fontSize": 0
    },
    {
      "id": "n13",
      "shape": "rect",
      "color": "blue",
      "x": 794.1471010578441,
      "y": 690.0168657233942,
      "w": 160,
      "h": 92.77999999999986,
      "title": "Proyectar convenio o contrato",
      "sub": "Área jurídica- Director - Entidades participantes",
      "info": "Revisión de términos por parte de la asesoría jurídica correspondiente o quien haga sus veces si se va a suscribir acuerdo de voluntades, tenga en cuenta el procedimiento U.PR.13.004.001 Asesoría Jurídica, cuando así lo requiera la negociación del proyecto. \n\nSuscribir el Acuerdo de Voluntades con la entidad externa, debe observarse lo dispuesto en el Manual de Convenios y Contratos, resolución 1551 de 2014, tramitar las pólizas necesarias y realizar los demás trámites que se requieran. \n\n",
      "consideraciones": "Actividades relacionadas: \n- Cuando se trata de dos o más Sedes, Facultades, Institutos o Centros (FIC) que participen en un mismo acuerdo de voluntades, se acuerda la FIC líder para firmar el acuerdo Inter-FIC. La FIC líder debe crear el proyecto en el sistema HERMES y asociar a las FIC participantes para que registren en el sistema las actividades correspondientes con sus responsabilidades.\n\n- Registrar en el sistema HERMES la aprobación de la entidad externa, la aprobación de Consejo, el acuerdo de voluntades y el acta de inicio cuando corresponda. ",
      "normativa": [
        "Manual de Convenios y Contratos",
        "Resolución 1551 de 2014"
      ],
      "durVal": 2,
      "durUnit": "d",
      "fontFamily": "",
      "fontSize": 0
    },
    {
      "id": "n14",
      "shape": "diamond",
      "color": "blue",
      "x": 485.95217446641664,
      "y": 1537.9577778329533,
      "w": 170,
      "h": 90,
      "title": "¿El consejo recomienda solicitud?",
      "sub": "",
      "info": "",
      "consideraciones": "",
      "normativa": [],
      "durVal": 0,
      "durUnit": "min",
      "fontFamily": "",
      "fontSize": 0
    },
    {
      "id": "n15",
      "shape": "rect",
      "color": "blue",
      "x": 794.1471010578441,
      "y": 836.3677153224422,
      "w": 160,
      "h": 69.67999999999998,
      "title": "Revisión de términos jurídicos",
      "sub": "Área jurídica",
      "info": "",
      "consideraciones": "",
      "normativa": [],
      "durVal": 2,
      "durUnit": "d",
      "fontFamily": "",
      "fontSize": 0
    },
    {
      "id": "n17",
      "shape": "rect",
      "color": "blue",
      "x": 794.1471010578441,
      "y": 948.7811559840627,
      "w": 160,
      "h": 69.67999999999998,
      "title": "Firma de convenio o contrato",
      "sub": "Vicerector",
      "info": "",
      "consideraciones": "",
      "normativa": [],
      "durVal": 1,
      "durUnit": "d",
      "fontFamily": "",
      "fontSize": 0
    },
    {
      "id": "n18",
      "shape": "rect",
      "color": "blue",
      "x": 794.1471010578441,
      "y": 1058.422155984062,
      "w": 160,
      "h": 84.15764999999995,
      "title": "Gestionar pólizas y requisitos legales",
      "sub": "Dirección de investigación y extensión ",
      "info": "",
      "consideraciones": "",
      "normativa": [],
      "durVal": 1,
      "durUnit": "d",
      "fontFamily": "",
      "fontSize": 0
    },
    {
      "id": "n19",
      "shape": "rect",
      "color": "amber",
      "x": 1056.3643294651756,
      "y": 129.26235141406391,
      "w": 160,
      "h": 121.92559999999973,
      "title": "Diligenciar en el Sistema HERMES la resolución de distribución presupuestal.",
      "sub": "Docente Director",
      "info": "",
      "consideraciones": "",
      "normativa": [],
      "durVal": 1,
      "durUnit": "d",
      "fontFamily": "",
      "fontSize": 0
    },
    {
      "id": "n20",
      "shape": "rect",
      "color": "amber",
      "x": 1056.3643294651756,
      "y": 294.0739999999988,
      "w": 160,
      "h": 81.99999999999986,
      "title": "Revisión de la distribución presupuestal",
      "sub": "Dirección Financiera",
      "info": "",
      "consideraciones": "",
      "normativa": [],
      "durVal": 3,
      "durUnit": "d",
      "fontFamily": "",
      "fontSize": 0
    },
    {
      "id": "n21",
      "shape": "rect",
      "color": "amber",
      "x": 1056.3643294651756,
      "y": 426.5329999999983,
      "w": 160,
      "h": 60,
      "title": "Firma de la resolución",
      "sub": "Vicerrector",
      "info": "",
      "consideraciones": "",
      "normativa": [],
      "durVal": 1,
      "durUnit": "d",
      "fontFamily": "",
      "fontSize": 0
    },
    {
      "id": "n22",
      "shape": "rect",
      "color": "amber",
      "x": 1056.3643294651756,
      "y": 531.681999999998,
      "w": 160,
      "h": 67.99999999999994,
      "title": "Registrar la ficha financiera en QUIPU",
      "sub": "Dirección Financiera",
      "info": "",
      "consideraciones": "",
      "normativa": [],
      "durVal": 1,
      "durUnit": "d",
      "fontFamily": "",
      "fontSize": 0
    },
    {
      "id": "n23",
      "shape": "rect",
      "color": "amber",
      "x": 1056.3643294651756,
      "y": 643.5638164574408,
      "w": 160,
      "h": 79.99999999999987,
      "title": "Iniciar ejecución financiera y administrativa",
      "sub": "Docente Director",
      "info": "",
      "consideraciones": "",
      "normativa": [],
      "durVal": 0,
      "durUnit": "min",
      "fontFamily": "",
      "fontSize": 0
    },
    {
      "id": "n24",
      "shape": "rect",
      "color": "green",
      "x": 1409.686856289573,
      "y": 142.68665520699943,
      "w": 160,
      "h": 75.3999999999999,
      "title": "Desarrollar actividades técnicas del proyecto",
      "sub": "Docente director",
      "info": "Si el proyecto requiere modificaciones, se registra en el sistema HERMES.",
      "consideraciones": "",
      "normativa": [],
      "durVal": 0,
      "durUnit": "min",
      "fontFamily": "",
      "fontSize": 0
    },
    {
      "id": "n25",
      "shape": "rect",
      "color": "green",
      "x": 1409.686856289573,
      "y": 244.3679999999989,
      "w": 160,
      "h": 102.3099999999997,
      "title": "Registrar modificaciones u otrosí en caso de ser requerido",
      "sub": "Docente director",
      "info": "",
      "consideraciones": "",
      "normativa": [],
      "durVal": 10,
      "durUnit": "d",
      "fontFamily": "",
      "fontSize": 0
    },
    {
      "id": "n26",
      "shape": "rect",
      "color": "green",
      "x": 1409.686856289573,
      "y": 402.150999999998,
      "w": 160,
      "h": 93.27499999999976,
      "title": "Elaborar y registrar informes parciales y finales",
      "sub": "Docente director",
      "info": " Elaborar informes para presentar a la entidad externa y corregir a partir de los comentarios recibidos por la entidad, sí requiere. Registrar avances del proyecto en el sistema Hermes de acuerdo con lo pactado con la Entidad Contratante, correspondiente a informes parciales y final. Para el desarrollo del informe final siga el formato U.FT.06.005.005 del sistema HERMES y registrarlo en el sistema. ",
      "consideraciones": "Hacer seguimiento con la Entidad Externa a la entrega de productos académicos en los tiempos que corresponde, entrega de facturas y recepción de los recursos.  Para el seguimiento interno, siga el módulo de Seguimiento para avances técnico-financieros en el sistema HERMES. ",
      "normativa": [],
      "durVal": 2,
      "durUnit": "d",
      "fontFamily": "",
      "fontSize": 0
    },
    {
      "id": "n27",
      "shape": "rect",
      "color": "green",
      "x": 1409.686856289573,
      "y": 558.1809999999973,
      "w": 160,
      "h": 60,
      "title": "Seguimiento técnico y financiero ",
      "sub": "",
      "info": "",
      "consideraciones": "",
      "normativa": [],
      "durVal": 0,
      "durUnit": "min",
      "fontFamily": "",
      "fontSize": 0
    },
    {
      "id": "n28",
      "shape": "rect",
      "color": "green",
      "x": 1409.686856289573,
      "y": 667.040999999997,
      "w": 160,
      "h": 60,
      "title": "Registrar producto académicos",
      "sub": "",
      "info": "Registrar el Producto Académico del proyecto y su lugar de depósito en el sistema HERMES.  Actividades relacionadas: \n\n-Verificar si los productos entregados y producto académico son posibles de proteger o patentar.  \n\n-Presentar el producto académico al Supervisor, para recibir el visto bueno y registrarlo en el sistema HERMES.  \n\n-Socializar resultados y producto académico, tenga en cuenta las cláusulas pactadas de confidencialidad. Registrar medio de socialización en el sistema HERMES. ",
      "consideraciones": "",
      "normativa": [],
      "durVal": 0,
      "durUnit": "min",
      "fontFamily": "",
      "fontSize": 0
    },
    {
      "id": "n29",
      "shape": "rect",
      "color": "green",
      "x": 1409.686856289573,
      "y": 771.1409999999964,
      "w": 160,
      "h": 60,
      "title": "Visto bueno supervisor (CON SAR)",
      "sub": "",
      "info": "",
      "consideraciones": "",
      "normativa": [],
      "durVal": 0,
      "durUnit": "min",
      "fontFamily": "",
      "fontSize": 0
    },
    {
      "id": "n30",
      "shape": "rect",
      "color": "green",
      "x": 1409.686856289573,
      "y": 868.2319090909052,
      "w": 160,
      "h": 78.1818181818181,
      "title": "Recomendación y aprobación de producto académico ante CIE (SIN SAR)",
      "sub": "",
      "info": "",
      "consideraciones": "",
      "normativa": [],
      "durVal": 0,
      "durUnit": "min",
      "fontFamily": "",
      "fontSize": 0
    },
    {
      "id": "n31",
      "shape": "rect",
      "color": "green",
      "x": 1409.686856289573,
      "y": 978.0500909090865,
      "w": 160,
      "h": 89.09090909090895,
      "title": "Recomendación y aprobación de producto académico ante Consejo de sede (SIN SAR)",
      "sub": "",
      "info": "",
      "consideraciones": "",
      "normativa": [],
      "durVal": 0,
      "durUnit": "min",
      "fontFamily": "",
      "fontSize": 0
    },
    {
      "id": "n32",
      "shape": "rect",
      "color": "green",
      "x": 1409.686856289573,
      "y": 1096.6340798117844,
      "w": 160,
      "h": 60,
      "title": "Socializar resultados",
      "sub": "",
      "info": "",
      "consideraciones": "",
      "normativa": [],
      "durVal": 0,
      "durUnit": "min",
      "fontFamily": "",
      "fontSize": 0
    },
    {
      "id": "n33",
      "shape": "rect",
      "color": "green",
      "x": 1742.8895201415935,
      "y": 172.91507981178881,
      "w": 160,
      "h": 79.96499999999986,
      "title": "Solicitar certificación y encuesta de satisfacción",
      "sub": "Docente Director",
      "info": " Solicitar certificación de cumplimiento y diligenciar el formato de satisfacción de usuario U.FT.06.005.004 del sistema SoftExpert o el formato establecido por parte de las Facultades, Centros e Institutos",
      "consideraciones": "Tener en cuenta el registro de la información relacionada con el impacto real del proyecto, teniendo en cuenta el impacto esperado de la etapa de formulación. ",
      "normativa": [],
      "durVal": 3,
      "durUnit": "d",
      "fontFamily": "",
      "fontSize": 0
    },
    {
      "id": "n34",
      "shape": "rect",
      "color": "green",
      "x": 1742.8895201415935,
      "y": 303.40199999999834,
      "w": 160,
      "h": 79.03329999999987,
      "title": "Liquidación contractual con entidad externa",
      "sub": "",
      "info": "Liquidar con la Entidad Contratante, realizar el proceso de liquidación contractual y firmar la respectiva acta de terminación y liquidación con la entidad.",
      "consideraciones": "",
      "normativa": [],
      "durVal": 3,
      "durUnit": "sem",
      "fontFamily": "",
      "fontSize": 0
    },
    {
      "id": "n35",
      "shape": "rect",
      "color": "green",
      "x": 1742.8895201415935,
      "y": 412.30199999999786,
      "w": 160,
      "h": 60,
      "title": "Liquidación financiera interna",
      "sub": "",
      "info": " Liquidación con la Universidad, seguir el procedimiento de liquidación financiera de proyectos U.PR.12.001.039 de la Gerencia Financiera y Administrativa y tener en cuenta los lineamientos dados por la Circular 36 de 2010 de la Gerencia Nacional Financiera. ",
      "consideraciones": "",
      "normativa": [
        "Circular 36 de 2010"
      ],
      "durVal": 3,
      "durUnit": "sem",
      "fontFamily": "",
      "fontSize": 0
    },
    {
      "id": "n36",
      "shape": "rect",
      "color": "green",
      "x": 1742.8895201415935,
      "y": 509.10199999999736,
      "w": 160,
      "h": 60,
      "title": "Emitir resolución y verificar ATI",
      "sub": "",
      "info": "",
      "consideraciones": "",
      "normativa": [
        "Acuerdo 036 de 2009"
      ],
      "durVal": 0,
      "durUnit": "min",
      "fontFamily": "",
      "fontSize": 0
    },
    {
      "id": "n37",
      "shape": "rect",
      "color": "green",
      "x": 1742.8895201415935,
      "y": 620.2019999999968,
      "w": 160,
      "h": 60,
      "title": "Conservar soportes documentales",
      "sub": "",
      "info": "",
      "consideraciones": "",
      "normativa": [],
      "durVal": 0,
      "durUnit": "min",
      "fontFamily": "",
      "fontSize": 0
    },
    {
      "id": "n38",
      "shape": "rect",
      "color": "green",
      "x": 1742.8895201415935,
      "y": 710.4019999999964,
      "w": 160,
      "h": 60,
      "title": "Acreditar experiencia institucional",
      "sub": "",
      "info": "Para tramitar RUP y acreditar la experiencia de la Universidad, siga la “Guía lineamientos generales para la selección de soportes RUP-UN”. ",
      "consideraciones": "",
      "normativa": [],
      "durVal": 1,
      "durUnit": "mes",
      "fontFamily": "",
      "fontSize": 0
    },
    {
      "id": "n40",
      "shape": "rect",
      "color": "blue",
      "x": 257.60330578512367,
      "y": 1272.4793388429741,
      "w": 160,
      "h": 67.43801652892562,
      "title": "El director debe corregir ",
      "sub": "Director ",
      "info": "",
      "consideraciones": "",
      "normativa": [],
      "durVal": 1,
      "durUnit": "d",
      "fontFamily": "",
      "fontSize": 0
    },
    {
      "id": "n41",
      "shape": "rect",
      "color": "blue",
      "x": 247.60330578512372,
      "y": 1548.479338842974,
      "w": 160,
      "h": 67.43801652892562,
      "title": "El director debe corregir ",
      "sub": "Director ",
      "info": "",
      "consideraciones": "",
      "normativa": [],
      "durVal": 1,
      "durUnit": "d",
      "fontFamily": "",
      "fontSize": 0
    }
  ],
  "conns": [
    {
      "id": "c1",
      "from": "n1",
      "fromPort": "bottom",
      "to": "n2",
      "toPort": "top",
      "style": "straight",
      "dash": "solid",
      "arrowEnd": "filled",
      "color": "#1a1917",
      "weight": 2,
      "label": ""
    },
    {
      "id": "c2",
      "from": "n2",
      "fromPort": "bottom",
      "to": "n3",
      "toPort": "top",
      "style": "straight",
      "dash": "solid",
      "arrowEnd": "filled",
      "color": "#1a1917",
      "weight": 2,
      "label": ""
    },
    {
      "id": "c3",
      "from": "n3",
      "fromPort": "bottom",
      "to": "n4",
      "toPort": "top",
      "style": "straight",
      "dash": "solid",
      "arrowEnd": "filled",
      "color": "#1a1917",
      "weight": 2,
      "label": "Sí"
    },
    {
      "id": "c4",
      "from": "n9",
      "fromPort": "bottom",
      "to": "n12",
      "toPort": "top",
      "style": "straight",
      "dash": "solid",
      "arrowEnd": "filled",
      "color": "#1a1917",
      "weight": 2,
      "label": ""
    },
    {
      "id": "c5",
      "from": "n12",
      "fromPort": "bottom",
      "to": "n10",
      "toPort": "top",
      "style": "straight",
      "dash": "solid",
      "arrowEnd": "filled",
      "color": "#1a1917",
      "weight": 2,
      "label": "Sí"
    },
    {
      "id": "c6",
      "from": "n10",
      "fromPort": "bottom",
      "to": "n14",
      "toPort": "top",
      "style": "straight",
      "dash": "solid",
      "arrowEnd": "filled",
      "color": "#1a1917",
      "weight": 2,
      "label": ""
    },
    {
      "id": "c8",
      "from": "n13",
      "fromPort": "bottom",
      "to": "n15",
      "toPort": "top",
      "style": "straight",
      "dash": "solid",
      "arrowEnd": "filled",
      "color": "#1a1917",
      "weight": 2,
      "label": ""
    },
    {
      "id": "c9",
      "from": "n15",
      "fromPort": "bottom",
      "to": "n17",
      "toPort": "top",
      "style": "straight",
      "dash": "solid",
      "arrowEnd": "filled",
      "color": "#1a1917",
      "weight": 2,
      "label": ""
    },
    {
      "id": "c10",
      "from": "n17",
      "fromPort": "bottom",
      "to": "n18",
      "toPort": "top",
      "style": "straight",
      "dash": "solid",
      "arrowEnd": "filled",
      "color": "#1a1917",
      "weight": 2,
      "label": ""
    },
    {
      "id": "c11",
      "from": "n4",
      "fromPort": "bottom",
      "to": "n5",
      "toPort": "top",
      "style": "straight",
      "dash": "solid",
      "arrowEnd": "filled",
      "color": "#1a1917",
      "weight": 2,
      "label": ""
    },
    {
      "id": "c12",
      "from": "n5",
      "fromPort": "bottom",
      "to": "n6",
      "toPort": "top",
      "style": "straight",
      "dash": "solid",
      "arrowEnd": "filled",
      "color": "#1a1917",
      "weight": 2,
      "label": ""
    },
    {
      "id": "c13",
      "from": "n6",
      "fromPort": "bottom",
      "to": "n7",
      "toPort": "top",
      "style": "straight",
      "dash": "solid",
      "arrowEnd": "filled",
      "color": "#1a1917",
      "weight": 2,
      "label": ""
    },
    {
      "id": "c14",
      "from": "n7",
      "fromPort": "bottom",
      "to": "n8",
      "toPort": "top",
      "style": "straight",
      "dash": "solid",
      "arrowEnd": "filled",
      "color": "#1a1917",
      "weight": 2,
      "label": ""
    },
    {
      "id": "c15",
      "from": "n8",
      "fromPort": "bottom",
      "to": "n9",
      "toPort": "top",
      "style": "straight",
      "dash": "solid",
      "arrowEnd": "filled",
      "color": "#1a1917",
      "weight": 2,
      "label": ""
    },
    {
      "id": "c16",
      "from": "n14",
      "fromPort": "right",
      "to": "n13",
      "toPort": "left",
      "style": "ortho",
      "dash": "dotted",
      "arrowEnd": "filled",
      "color": "#1a1917",
      "weight": 2,
      "label": "Sí"
    },
    {
      "id": "c18",
      "from": "n12",
      "fromPort": "left",
      "to": "n40",
      "toPort": "right",
      "style": "straight",
      "dash": "solid",
      "arrowEnd": "filled",
      "color": "#1a1917",
      "weight": 2,
      "label": "No"
    },
    {
      "id": "c19",
      "from": "n40",
      "fromPort": "top",
      "to": "n9",
      "toPort": "left",
      "style": "ortho",
      "dash": "solid",
      "arrowEnd": "filled",
      "color": "#1a1917",
      "weight": 2,
      "label": ""
    },
    {
      "id": "c20",
      "from": "n14",
      "fromPort": "left",
      "to": "n41",
      "toPort": "right",
      "style": "straight",
      "dash": "solid",
      "arrowEnd": "filled",
      "color": "#1a1917",
      "weight": 2,
      "label": "No"
    },
    {
      "id": "c21",
      "from": "n41",
      "fromPort": "top",
      "to": "n10",
      "toPort": "left",
      "style": "ortho",
      "dash": "solid",
      "arrowEnd": "filled",
      "color": "#1a1917",
      "weight": 2,
      "label": ""
    },
    {
      "id": "c23",
      "from": "n19",
      "fromPort": "bottom",
      "to": "n20",
      "toPort": "top",
      "style": "ortho",
      "dash": "solid",
      "arrowEnd": "filled",
      "color": "#1a1917",
      "weight": 2,
      "label": ""
    },
    {
      "id": "c24",
      "from": "n20",
      "fromPort": "bottom",
      "to": "n21",
      "toPort": "top",
      "style": "ortho",
      "dash": "solid",
      "arrowEnd": "filled",
      "color": "#1a1917",
      "weight": 2,
      "label": ""
    },
    {
      "id": "c25",
      "from": "n21",
      "fromPort": "bottom",
      "to": "n22",
      "toPort": "top",
      "style": "ortho",
      "dash": "solid",
      "arrowEnd": "filled",
      "color": "#1a1917",
      "weight": 2,
      "label": ""
    },
    {
      "id": "c26",
      "from": "n22",
      "fromPort": "bottom",
      "to": "n23",
      "toPort": "top",
      "style": "ortho",
      "dash": "solid",
      "arrowEnd": "filled",
      "color": "#1a1917",
      "weight": 2,
      "label": ""
    },
    {
      "id": "c27",
      "from": "n23",
      "fromPort": "right",
      "to": "n24",
      "toPort": "left",
      "style": "ortho",
      "dash": "dotted",
      "arrowEnd": "filled",
      "color": "#1a1917",
      "weight": 2,
      "label": ""
    },
    {
      "id": "c28",
      "from": "n24",
      "fromPort": "bottom",
      "to": "n25",
      "toPort": "top",
      "style": "ortho",
      "dash": "solid",
      "arrowEnd": "filled",
      "color": "#1a1917",
      "weight": 2,
      "label": ""
    },
    {
      "id": "c29",
      "from": "n25",
      "fromPort": "bottom",
      "to": "n26",
      "toPort": "top",
      "style": "straight",
      "dash": "solid",
      "arrowEnd": "filled",
      "color": "#1a1917",
      "weight": 2,
      "label": ""
    },
    {
      "id": "c30",
      "from": "n26",
      "fromPort": "bottom",
      "to": "n27",
      "toPort": "top",
      "style": "straight",
      "dash": "solid",
      "arrowEnd": "filled",
      "color": "#1a1917",
      "weight": 2,
      "label": ""
    },
    {
      "id": "c31",
      "from": "n27",
      "fromPort": "bottom",
      "to": "n28",
      "toPort": "top",
      "style": "straight",
      "dash": "solid",
      "arrowEnd": "filled",
      "color": "#1a1917",
      "weight": 2,
      "label": ""
    },
    {
      "id": "c32",
      "from": "n28",
      "fromPort": "bottom",
      "to": "n29",
      "toPort": "top",
      "style": "straight",
      "dash": "solid",
      "arrowEnd": "filled",
      "color": "#1a1917",
      "weight": 2,
      "label": ""
    },
    {
      "id": "c33",
      "from": "n29",
      "fromPort": "bottom",
      "to": "n30",
      "toPort": "top",
      "style": "straight",
      "dash": "solid",
      "arrowEnd": "filled",
      "color": "#1a1917",
      "weight": 2,
      "label": ""
    },
    {
      "id": "c34",
      "from": "n30",
      "fromPort": "bottom",
      "to": "n31",
      "toPort": "top",
      "style": "straight",
      "dash": "solid",
      "arrowEnd": "filled",
      "color": "#1a1917",
      "weight": 2,
      "label": ""
    },
    {
      "id": "c35",
      "from": "n31",
      "fromPort": "bottom",
      "to": "n32",
      "toPort": "top",
      "style": "straight",
      "dash": "solid",
      "arrowEnd": "filled",
      "color": "#1a1917",
      "weight": 2,
      "label": ""
    },
    {
      "id": "c36",
      "from": "n32",
      "fromPort": "right",
      "to": "n33",
      "toPort": "left",
      "style": "ortho",
      "dash": "dotted",
      "arrowEnd": "filled",
      "color": "#1a1917",
      "weight": 2,
      "label": ""
    },
    {
      "id": "c37",
      "from": "n33",
      "fromPort": "bottom",
      "to": "n34",
      "toPort": "top",
      "style": "straight",
      "dash": "solid",
      "arrowEnd": "filled",
      "color": "#1a1917",
      "weight": 2,
      "label": ""
    },
    {
      "id": "c38",
      "from": "n34",
      "fromPort": "bottom",
      "to": "n35",
      "toPort": "top",
      "style": "ortho",
      "dash": "solid",
      "arrowEnd": "filled",
      "color": "#1a1917",
      "weight": 2,
      "label": ""
    },
    {
      "id": "c39",
      "from": "n35",
      "fromPort": "bottom",
      "to": "n36",
      "toPort": "top",
      "style": "ortho",
      "dash": "solid",
      "arrowEnd": "filled",
      "color": "#1a1917",
      "weight": 2,
      "label": ""
    },
    {
      "id": "c40",
      "from": "n36",
      "fromPort": "bottom",
      "to": "n37",
      "toPort": "top",
      "style": "ortho",
      "dash": "solid",
      "arrowEnd": "filled",
      "color": "#1a1917",
      "weight": 2,
      "label": ""
    },
    {
      "id": "c41",
      "from": "n37",
      "fromPort": "bottom",
      "to": "n38",
      "toPort": "top",
      "style": "ortho",
      "dash": "solid",
      "arrowEnd": "filled",
      "color": "#1a1917",
      "weight": 2,
      "label": ""
    },
    {
      "id": "c42",
      "from": "n17",
      "fromPort": "right",
      "to": "n19",
      "toPort": "left",
      "style": "ortho",
      "dash": "dotted",
      "arrowEnd": "filled",
      "color": "#1a1917",
      "weight": 2,
      "label": ""
    }
  ],
  "nid": 41,
  "cid": 42,
  "v": 1,
  "ts": 1783113174477
}